{
    "210000": {
        "id": 210000,
        "group": "失控",
        "name": "时间线",
        "desc": "在一切的开始，旅途始发于此。",
        "unlock_desc": "默认解锁",
        "bpm": 112
    },
    "210001": {
        "id": 210001,
        "group": "失控",
        "name": "灾虐的黎明",
        "desc": "灾难过后，只有极少数人愿意去探究这究竟是无妄之灾，抑或是他人的算计。",
        "unlock_desc": "探索空间站「黑塔」基座舱段获得",
        "bpm": 130
    },
    "210002": {
        "id": 210002,
        "group": "失控",
        "name": "好戏开场",
        "desc": "泡泡糖、薯片，再加上冰汽水，一切就绪，银狼最喜欢的画面即将播映。",
        "unlock_desc": "默认解锁",
        "bpm": 128
    },
    "210003": {
        "id": 210003,
        "group": "失控",
        "name": "即兴演出",
        "desc": "人生如戏，全靠演技。即使是最诚实的人，也会有需要即兴出演的时刻。",
        "unlock_desc": "完成同行任务「阴差阳错」获得",
        "bpm": 128
    },
    "210004": {
        "id": 210004,
        "group": "失控",
        "name": "科幻小说",
        "desc": "幻想多么希望把世界引入迷途,而科学缓慢而又清醒地选择了它的路。",
        "unlock_desc": "默认解锁",
        "bpm": 80
    },
    "210005": {
        "id": 210005,
        "group": "失控",
        "name": "太空漫步",
        "desc": "踏出舱外一步登天，超越光年漂流星间。",
        "unlock_desc": "默认解锁",
        "bpm": 80
    },
    "210006": {
        "id": 210006,
        "group": "失控",
        "name": "盐渍月亮",
        "desc": "配方是：野火浸泡的龙舌兰，加上背负命案的柠檬片，还有一把星星眼泪酿成的盐。",
        "unlock_desc": "默认解锁",
        "bpm": 122
    },
    "210007": {
        "id": 210007,
        "group": "失控",
        "name": "踏上旅途",
        "desc": "没有人知道旅途的前方等待自己的会是什么，因此仅仅是踏出这一步就足以令人恐惧。",
        "unlock_desc": "默认解锁",
        "bpm": 74
    },
    "210008": {
        "id": 210008,
        "group": "失控",
        "name": "危机预知",
        "desc": "如果能预知到未来的危机与风险…但很可惜，并没有「如果」。",
        "unlock_desc": "探索空间站「黑塔」主控舱段获得",
        "bpm": 134
    },
    "210010": {
        "id": 210010,
        "group": "失控",
        "name": "重力丧失",
        "desc": "重力改变的瞬间，甚至连呼吸都已忘却。",
        "unlock_desc": "完成同行任务「知名不具」获得",
        "bpm": 141
    },
    "210100": {
        "id": 210100,
        "group": "雪融于烬",
        "name": "秩序",
        "desc": "和抵挡风雪的高墙一样，秩序由筑城者们亲自建立。",
        "unlock_desc": "贝洛伯格「行政区商店」购买获得",
        "bpm": 109
    },
    "210101": {
        "id": 210101,
        "group": "雪融于烬",
        "name": "火种",
        "desc": "风雪无法浇灭所有的温暖，最后的火种自地底升腾而起。",
        "unlock_desc": "完成同行任务「风雪免疫」获得",
        "bpm": 159
    },
    "210102": {
        "id": 210102,
        "group": "雪融于烬",
        "name": "地下",
        "desc": "地表之下的世界，仍然有人在坚守着自己的家园。",
        "unlock_desc": "完成同行任务「虎克的礼物」获得",
        "bpm": 124
    },
    "210103": {
        "id": 210103,
        "group": "雪融于烬",
        "name": "教父",
        "desc": "以他力量所做的一切事情，也只是为了保护他的家人。",
        "unlock_desc": "完成同行任务「难得有情•其一」获得",
        "bpm": 130
    },
    "210104": {
        "id": 210104,
        "group": "雪融于烬",
        "name": "严寒行军",
        "desc": "「为何在面对不可抗辩的力量时，我们想到的第一件事永远是抗拒、堵上耳朵，而非聆听它的诉求？」",
        "unlock_desc": "完成同行任务「只是孩子」获得",
        "bpm": 114
    },
    "210105": {
        "id": 210105,
        "group": "雪融于烬",
        "name": "陷阵无回",
        "desc": "「祂的力量与我同在…你们不过是旧世界崩溃前的垂死挣扎！」",
        "unlock_desc": "完成开拓任务「静静的星河」获得",
        "bpm": 72
    },
    "210106": {
        "id": 210106,
        "group": "雪融于烬",
        "name": "野火",
        "desc": "「不破其旧，无以立新。」",
        "unlock_desc": "完成开拓任务「静静的星河」获得",
        "bpm": 72
    },
    "210107": {
        "id": 210107,
        "group": "雪融于烬",
        "name": "苍逝冷阳",
        "desc": "贝洛伯格的今时与往日并无太大区别，唯一不同的或许只有越发寒冷的夜。",
        "unlock_desc": "完成开拓任务「他们有多少人已掉进深渊」获得",
        "bpm": 104
    },
    "210108": {
        "id": 210108,
        "group": "雪融于烬",
        "name": "旧日之影",
        "desc": "覆灭的阴影始终在贝洛伯格城外徘徊。",
        "unlock_desc": "完成开拓任务「已故去的必如雪崩再来」获得",
        "bpm": 77
    },
    "210109": {
        "id": 210109,
        "group": "雪融于烬",
        "name": "永冬",
        "desc": "未曾停息的寒潮之下，人类的生存空间愈发狭小。",
        "unlock_desc": "完成开拓任务「回归」获得",
        "bpm": 68
    },
    "210110": {
        "id": 210110,
        "group": "雪融于烬",
        "name": "命途",
        "desc": "抉择的时刻降临，迈向未来的道路明明这么近，却又那么远。",
        "unlock_desc": "完成开拓任务「回归」获得",
        "bpm": 65
    },
    "210111": {
        "id": 210111,
        "group": "雪融于烬",
        "name": "余烬",
        "desc": "在温暖的余烬前度过平凡的一天，对某些人群而言也是种奢念。",
        "unlock_desc": "探索贝洛伯格黄金歌剧院区域获得",
        "bpm": 98
    },
    "210112": {
        "id": 210112,
        "group": "雪融于烬",
        "name": "炉火",
        "desc": "幸福很简单，身边有炉火的噼啪声和亲朋好友的陪伴就够了。",
        "unlock_desc": "贝洛伯格「小吃摊」购买获得",
        "bpm": 99
    },
    "210113": {
        "id": 210113,
        "group": "雪融于烬",
        "name": "暖阳",
        "desc": "美好时光就像冬日的暖阳，脆弱短暂，却以刹那的温暖抚平了岁月的艰难漫长。",
        "unlock_desc": "探索贝洛伯格花店「长夏」区域获得",
        "bpm": 96
    },
    "210114": {
        "id": 210114,
        "group": "雪融于烬",
        "name": "喧哗",
        "desc": "只有燃起舞蹈的篝火，人们才不会被这颗冰冷的星球遗忘。",
        "unlock_desc": "完成开拓任务「从凶险和泥泞的沼泽中」获得",
        "bpm": 120
    },
    "210115": {
        "id": 210115,
        "group": "雪融于烬",
        "name": "酣眠",
        "desc": "梦向风雪深处蜿蜒，逝者于此喃喃低语。",
        "unlock_desc": "探索贝洛伯格历史文化博物馆区域获得",
        "bpm": 70
    },
    "210200": {
        "id": 210200,
        "group": "长生梦短",
        "name": "云阵四合",
        "desc": "天高烟敛，怎料快雨还晴。云生云灭，又逢世事如谜。",
        "unlock_desc": "完成开拓任务「紫府通谒，将军定策」获得",
        "bpm": 118
    },
    "210201": {
        "id": 210201,
        "group": "长生梦短",
        "name": "星文照旅魂",
        "desc": "一路经行处，星文照旅魂。",
        "unlock_desc": "完成开拓任务「迴星周旋，未卜知先」获得",
        "bpm": 84
    },
    "210202": {
        "id": 210202,
        "group": "长生梦短",
        "name": "俯仰穷观",
        "desc": "仰观天文，俯察地理，幽明之故，自在应心。",
        "unlock_desc": "完成开拓任务「神木重萌，掣转天衡」获得",
        "bpm": 68
    },
    "210203": {
        "id": 210203,
        "group": "长生梦短",
        "name": "玲珑工巧",
        "desc": "量浮槎之任，视木之能举，盈尺而曲尽其制，计其毫厘筑洞天。",
        "unlock_desc": "完成开拓任务「极数问玄，历事穷观」获得",
        "bpm": 74
    },
    "210204": {
        "id": 210204,
        "group": "长生梦短",
        "name": "天下熙熙",
        "desc": "日月盈昃，银汉昭昭。寒来暑往，天下熙熙。",
        "unlock_desc": "仙舟「罗浮」「杂货小摊」购买获得",
        "bpm": 108
    },
    "210205": {
        "id": 210205,
        "group": "长生梦短",
        "name": "襟怀玉界",
        "desc": "星河斗转，人间帘垂。",
        "unlock_desc": "完成同行任务「因为我已触碰过天空」获得",
        "bpm": 68
    },
    "210206": {
        "id": 210206,
        "group": "长生梦短",
        "name": "鹤唳",
        "desc": "长风至而波起兮，草木震动，山鸣谷应。",
        "unlock_desc": "完成同行任务「异邦骑士」获得",
        "bpm": 145
    },
    "210207": {
        "id": 210207,
        "group": "长生梦短",
        "name": "青锋急急如律令",
        "desc": "尺水驻烟柳，流光出宝匣。",
        "unlock_desc": "完成同行任务「霜刃一试」获得",
        "bpm": 145
    },
    "210208": {
        "id": 210208,
        "group": "长生梦短",
        "name": "逐鹿",
        "desc": "鹿死不择音。",
        "unlock_desc": "完成开拓任务「茸客鸣呦，玉角盘虬」获得",
        "bpm": 170
    },
    "210209": {
        "id": 210209,
        "group": "长生梦短",
        "name": "邀挽明月成宵宴",
        "desc": "清夜无尘。月色如银。酒斟时、须满十分。",
        "unlock_desc": "完成开拓任务「极数问玄，历事穷观」获得",
        "bpm": 102
    },
    "210210": {
        "id": 210210,
        "group": "长生梦短",
        "name": "折冲妙算",
        "desc": "便纵有、须臾万变，仅凭神谋。",
        "unlock_desc": "探索仙舟「罗浮」神策府获得",
        "bpm": 104
    },
    "210211": {
        "id": 210211,
        "group": "长生梦短",
        "name": "雷车动地",
        "desc": "洊雷出滞，曜电奔涌。",
        "unlock_desc": "探索仙舟「罗浮」星槎海中枢获得",
        "bpm": 116
    },
    "210212": {
        "id": 210212,
        "group": "长生梦短",
        "name": "猎手的预视",
        "desc": "正眼从来付猎人。",
        "unlock_desc": "完成同行任务「陌生女人的来信」获得",
        "bpm": 143
    },
    "210213": {
        "id": 210213,
        "group": "长生梦短",
        "name": "锋镝阵中自在身",
        "desc": "心畅百戈销，境闲沙场静。",
        "unlock_desc": "完成同行任务「譬如朝露」获得",
        "bpm": 128
    },
    "210214": {
        "id": 210214,
        "group": "长生梦短",
        "name": "药王救世陀罗尼",
        "desc": "药王慈怀，建木生发。莳者一心，同登极乐。",
        "unlock_desc": "完成开拓任务「金鼎灵树，穷途梼杌」获得",
        "bpm": 134
    },
    "210215": {
        "id": 210215,
        "group": "长生梦短",
        "name": "解脱妙谛",
        "desc": "犹滞幻形，人间从来一梦。破妄显真，归觉药王大道。",
        "unlock_desc": "完成开拓任务「有龙矫矫，其渊渺渺」后，可在仙舟「罗浮」「三余书肆」购买获得",
        "bpm": 146
    },
    "210216": {
        "id": 210216,
        "group": "长生梦短",
        "name": "弹铗飞光现龙影",
        "desc": "少年任气侠，由来万夫勇。",
        "unlock_desc": "完成开拓任务「有龙矫矫，其渊渺渺」后，可在仙舟「罗浮」「三余书肆」购买获得",
        "bpm": 170
    },
    "210217": {
        "id": 210217,
        "group": "长生梦短",
        "name": "烟霞逝梦",
        "desc": "人生似幻化，终当归空无。",
        "unlock_desc": "完成开拓任务「有龙矫矫，其渊渺渺」后，可在仙舟「罗浮」「三余书肆」购买获得",
        "bpm": 105
    },
    "210218": {
        "id": 210218,
        "group": "长生梦短",
        "name": "古海宫墟",
        "desc": "龙返其乡，终不见处所。",
        "unlock_desc": "完成冒险任务「陶德•雷奥登的学术研究：龙图三变」获得",
        "bpm": 150
    },
    "210219": {
        "id": 210219,
        "group": "长生梦短",
        "name": "水龙吟",
        "desc": "天渊一啸，万古潮动。",
        "unlock_desc": "完成同行任务「龙返其乡」获得",
        "bpm": 95
    },
    "210220": {
        "id": 210220,
        "group": "长生梦短",
        "name": "海若隐珠",
        "desc": "烟波如谜，千代不复还。渊珠成泪，万灵同此哀。",
        "unlock_desc": "完成冒险任务「动物凶猛•落幕」获得",
        "bpm": 64
    },
    "210221": {
        "id": 210221,
        "group": "长生梦短",
        "name": "玄牝之门，万类之根",
        "desc": "烟萝玉树朽再生，长生旧梦醒复眠。",
        "unlock_desc": "完成开拓任务「有龙矫矫，其渊渺渺」后，可在仙舟「罗浮」「三余书肆」购买获得",
        "bpm": 60
    },
    "210222": {
        "id": 210222,
        "group": "长生梦短",
        "name": "蝉喓歌·晦明苦短",
        "desc": "朝幪幪，暮枯瘁。蜉蝣朝露，来日苦短。",
        "unlock_desc": "完成开拓任务「有龙矫矫，其渊渺渺」后，可在仙舟「罗浮」「三余书肆」购买获得",
        "bpm": 130
    },
    "210223": {
        "id": 210223,
        "group": "长生梦短",
        "name": "蝉喓歌·仙骸有终",
        "desc": "晦明兮苦短，魂魄兮爢散，日月兮昏乱，烛明还复燃。",
        "unlock_desc": "完成开拓任务「有龙矫矫，其渊渺渺」获得",
        "bpm": 140
    },
    "210224": {
        "id": 210224,
        "group": "长生梦短",
        "name": "蝉喓歌·长命无绝",
        "desc": "大劫渡厄，天无翳，四炁清。",
        "unlock_desc": "完成开拓任务「有龙矫矫，其渊渺渺」获得",
        "bpm": 160
    },
    "210225": {
        "id": 210225,
        "group": "长生梦短",
        "name": "载歌须纵酒",
        "desc": "云动笙歌起，诗成醉笔摇。",
        "unlock_desc": "完成冒险任务「金戺重喧•其四」获得",
        "bpm": 94
    },
    "210226": {
        "id": 210226,
        "group": "失控",
        "name": "宇宙殉情时",
        "desc": "忽有天顶如烟花炸开，爱与死亡一同绽放。",
        "unlock_desc": "完成同行任务「宇宙幻觉之夜」获得",
        "bpm": 120
    },
    "210227": {
        "id": 210227,
        "group": "失控",
        "name": "奇情异想的绅士",
        "desc": "这里是信仰与痛觉交织的银河黄金时代，他只留下了日笃疯癫的纯真。",
        "unlock_desc": "完成同行任务「宇宙幻觉之夜」获得",
        "bpm": 84
    },
    "210228": {
        "id": 210228,
        "group": "长生梦短",
        "name": "百鬼率舞",
        "desc": "予击石拊石，百鬼率舞。",
        "unlock_desc": "完成开拓续闻任务「游园惊梦」获得",
        "bpm": 147
    },
    "210229": {
        "id": 210229,
        "group": "长生梦短",
        "name": "眠鸥宿鹭",
        "desc": "眠鸥宿鹭，阒然无声。",
        "unlock_desc": "完成冒险任务「捉鬼小队•金色奖牌」获得",
        "bpm": 98
    }
}